python_seedwork_be/__init__.py
python_seedwork_be/adapters/__init__.py
python_seedwork_be/adapters/logger/__init__.py
python_seedwork_be/adapters/logger/abstract_logger.py
python_seedwork_be/adapters/logger/simple_logger.py
python_seedwork_be/adapters/messaging/__init__.py
python_seedwork_be/adapters/messaging/client_notification/AbstractUserNotificationPushDrivingAdapter.py
python_seedwork_be/adapters/messaging/client_notification/__init__.py
python_seedwork_be/adapters/messaging/notification/DefaultImplementNotificationApplicationService.py
python_seedwork_be/adapters/messaging/notification/EventHandlingTracker.py
python_seedwork_be/adapters/messaging/notification/KeyValueEventHandlingTracker.py
python_seedwork_be/adapters/messaging/notification/Notification.py
python_seedwork_be/adapters/messaging/notification/NotificationPublisher.py
python_seedwork_be/adapters/messaging/notification/NotificationReader.py
python_seedwork_be/adapters/messaging/notification/NotificationSerializer.py
python_seedwork_be/adapters/messaging/notification/PublishedNotificationTracker.py
python_seedwork_be/adapters/messaging/notification/PublishedNotificationTrackerStore.py
python_seedwork_be/adapters/messaging/notification/__init__.py
python_seedwork_be/adapters/persistance/__init__.py
python_seedwork_be/adapters/persistance/key_value/AbstractKeyValueRepository.py
python_seedwork_be/adapters/persistance/key_value/__init__.py
python_seedwork_be/adapters/persistance/sql/AbstractUnitOfWork.py
python_seedwork_be/adapters/persistance/sql/DBSessionUser.py
python_seedwork_be/adapters/persistance/sql/__init__.py
python_seedwork_be/application/AbstractApplicationLifeCycle.py
python_seedwork_be/application/ApplicationLifeCycleUseCase.py
python_seedwork_be/application/__init__.py
python_seedwork_be/application/command.py
python_seedwork_be/application/handler.py
python_seedwork_be/application/query.py
python_seedwork_be/application/service.py
python_seedwork_be/domain/AbstractDomainEventDict.py
python_seedwork_be-0.1.55.dist-info/LICENSE
python_seedwork_be-0.1.55.dist-info/METADATA
python_seedwork_be-0.1.55.dist-info/WHEEL
python_seedwork_be-0.1.55.dist-info/RECORD
